{
  "Comment": "Lady Glass document-level workflow. Step Functions orchestrates SubmitPages -> Wait -> CheckPages -> Choice -> Merge / MarkJobFailed. The optional RenderPages branch splits PDFs into per-page PDFs before SubmitPages when input.mode == 'rendered'. Per-page AI work happens entirely inside the SQS+Lambda chain, not in this state machine.",
  "StartAt": "ModeChoice",
  "States": {
    "ModeChoice": {
      "Type": "Choice",
      "Choices": [
        {
          "Variable": "$.mode",
          "StringEquals": "rendered",
          "Next": "RenderPages"
        }
      ],
      "Default": "SubmitPages"
    },
    "RenderPages": {
      "Type": "Task",
      "Resource": "${RenderPagesLambdaArn}",
      "Parameters": {
        "job_id.$": "$.job_id",
        "input_uri.$": "$.input_uri"
      },
      "ResultPath": "$.render_result",
      "Next": "SubmitPagesAfterRender"
    },
    "SubmitPagesAfterRender": {
      "Type": "Task",
      "Resource": "${SubmitPagesLambdaArn}",
      "Parameters": {
        "job_id.$": "$.job_id",
        "input_uri.$": "$.input_uri",
        "pages.$": "$.render_result.pages",
        "chain.$": "$.chain"
      },
      "ResultPath": "$.submit_result",
      "Next": "WaitForPages"
    },
    "SubmitPages": {
      "Type": "Task",
      "Resource": "${SubmitPagesLambdaArn}",
      "Parameters": {
        "job_id.$": "$.job_id",
        "input_uri.$": "$.input_uri",
        "pages.$": "$.pages",
        "chain.$": "$.chain"
      },
      "ResultPath": "$.submit_result",
      "Next": "WaitForPages"
    },
    "WaitForPages": {
      "Type": "Wait",
      "Seconds": 10,
      "Next": "CheckPages"
    },
    "CheckPages": {
      "Type": "Task",
      "Resource": "${CheckPagesLambdaArn}",
      "Parameters": {
        "job_id.$": "$.job_id",
        "page_count.$": "$.submit_result.page_count",
        "final_stage.$": "$.final_stage",
        "final_version.$": "$.final_version"
      },
      "ResultPath": "$.check_result",
      "Next": "JobStatus?"
    },
    "JobStatus?": {
      "Type": "Choice",
      "Choices": [
        {
          "Variable": "$.check_result.status",
          "StringEquals": "succeeded",
          "Next": "Merge"
        },
        {
          "Variable": "$.check_result.status",
          "StringEquals": "failed",
          "Next": "MarkJobFailed"
        }
      ],
      "Default": "WaitForPages"
    },
    "Merge": {
      "Type": "Task",
      "Resource": "${MergeLambdaArn}",
      "Parameters": {
        "job_id.$": "$.job_id",
        "page_count.$": "$.submit_result.page_count",
        "final_stage.$": "$.final_stage",
        "final_version.$": "$.final_version"
      },
      "End": true
    },
    "MarkJobFailed": {
      "Type": "Task",
      "Resource": "${MarkJobFailedLambdaArn}",
      "Parameters": {
        "job_id.$": "$.job_id",
        "error": "one or more page stages reported status=failed"
      },
      "End": true
    }
  }
}
